{
  "brand": "",
  "category": "",
  "crawledAt": "id_or_token",
  "currency": "CNY",
  "id": "7228993240...",
  "images": [
    "https://..."
  ],
  "isCustomized": true,
  "keywords": null,
  "mainImage": "https://...",
  "maxPrice": 10,
  "minOrderQuantity": 1,
  "minPrice": 10,
  "packInfo": {
    "instructions": "",
    "packageContents": [],
    "packageImages": null,
    "packageSize": null,
    "packageType": "标准包\ufffd...",
    "weight": 0.25
  },
  "priceRanges": [
    {
      "maxQuantity": 0,
      "minQuantity": 10,
      "price": 10
    }
  ],
  "productDetails": [
    {
      "content": "https://...",
      "images": [],
      "section": "详情链\ufffd..."
    }
  ],
  "rating": 0,
  "reviewCount": 0,
  "salesVolume": 0,
  "shippingInfo": {
    "isFreeShipping": false,
    "processingTime": "",
    "shippingFrom": "浙江省\ufffd...",
    "shippingMethods": null
  },
  "specifications": [
    {
      "name": "面料名\ufffd...",
      "value": "棉"
    }
  ],
  "supplier": {
    "cardType": "id_or_token",
    "companyName": "id_or_token",
    "id": "b2b-221548...",
    "isGoldSupplier": false,
    "isVerified": true,
    "location": "浙江省\ufffd...",
    "name": "义乌巨\ufffd...",
    "rating": 0,
    "responseRate": 0,
    "shopUrl": "https://...",
    "yearsInBusiness": 3
  },
  "title": "id_or_token",
  "unit": "件",
  "updatedAt": "id_or_token",
  "url": "https://...",
  "variants": [
    {
      "attributes": {
        "尺码": "儿童尺\ufffd...",
        "颜色": "id_or_token"
      },
      "image": "https://...",
      "name": "100%新疆...",
      "price": 10,
      "stock": 99999
    }
  ],
  "variationsValues": [
    {
      "values": [
        "id_or_token"
      ],
      "variant_name": "颜色"
    }
  ],
  "videos": [
    {
      "coverUrl": "https://...",
      "state": 0,
      "title": "id_or_token",
      "videoId": 0,
      "videoUrl": "https://..."
    }
  ]
}